mergekitty/__init__.py
mergekitty/architecture.py
mergekitty/card.py
mergekitty/common.py
mergekitty/config.py
mergekitty/merge.py
mergekitty/options.py
mergekitty/plan.py
mergekitty/sparsify.py
mergekitty/task.py
mergekitty/_data/__init__.py
mergekitty/_data/architectures/__init__.py
mergekitty/_data/architectures/baichuan.json
mergekitty/_data/architectures/bert-masked-lm.json
mergekitty/_data/architectures/bert-sequence-classification.json
mergekitty/_data/architectures/bert.json
mergekitty/_data/architectures/chatglm.json
mergekitty/_data/architectures/cohere.json
mergekitty/_data/architectures/distilbert-masked-lm.json
mergekitty/_data/architectures/distilbert-sequence-classification.json
mergekitty/_data/architectures/distilbert-token-classification.json
mergekitty/_data/architectures/distilbert.json
mergekitty/_data/architectures/exaone.json
mergekitty/_data/architectures/falcon.json
mergekitty/_data/architectures/gemma.json
mergekitty/_data/architectures/gemma2.json
mergekitty/_data/architectures/glm4.json
mergekitty/_data/architectures/gpt-neox.json
mergekitty/_data/architectures/gpt2-sequence-classification.json
mergekitty/_data/architectures/gpt2.json
mergekitty/_data/architectures/gptbigcode.json
mergekitty/_data/architectures/internlm2.json
mergekitty/_data/architectures/jais.json
mergekitty/_data/architectures/llama.json
mergekitty/_data/architectures/mamba.json
mergekitty/_data/architectures/mistral.json
mergekitty/_data/architectures/mixtral.json
mergekitty/_data/architectures/olmoe.json
mergekitty/_data/architectures/phi-1.json
mergekitty/_data/architectures/phi2-old.json
mergekitty/_data/architectures/phi2.json
mergekitty/_data/architectures/phi3-small.json
mergekitty/_data/architectures/phi3.json
mergekitty/_data/architectures/qwen.json
mergekitty/_data/architectures/qwen2.json
mergekitty/_data/architectures/qwen3.json
mergekitty/_data/architectures/qwen3moe.json
mergekitty/_data/architectures/roberta-masked-lm.json
mergekitty-0.1.0.dist-info/METADATA
mergekitty-0.1.0.dist-info/WHEEL
mergekitty-0.1.0.dist-info/entry_points.txt
mergekitty-0.1.0.dist-info/licenses/LICENSE
mergekitty-0.1.0.dist-info/RECORD
