Metadata-Version: 2.4
Name: mergekitty
Version: 0.1.0
Summary: Tools for merging pre-trained large language models
Project-URL: repository, https://github.com/allura-org/mergekitty
Author-email: fizz~ <fizzarolli@riseup.net>, Charles Goddard <chargoddard@gmail.com>
License: LGPL-3.0-or-later
License-File: LICENSE
Requires-Python: >=3.10
Requires-Dist: accelerate~=1.3.0
Requires-Dist: click==8.1.8
Requires-Dist: datasets
Requires-Dist: huggingface-hub
Requires-Dist: immutables==0.20
Requires-Dist: peft
Requires-Dist: protobuf
Requires-Dist: pydantic~=2.10.6
Requires-Dist: safetensors~=0.5.2
Requires-Dist: scipy
Requires-Dist: sentencepiece
Requires-Dist: tokenizers>=0.20.1
Requires-Dist: torch~=2.5.0
Requires-Dist: tqdm==4.67.1
Requires-Dist: transformers>=4.45.2
Requires-Dist: typing-extensions
Provides-Extra: dev
Requires-Dist: pre-commit~=4.1.0; extra == 'dev'
Requires-Dist: ruff~=0.9.4; extra == 'dev'
Provides-Extra: gradio
Requires-Dist: gradio-huggingfacehub-search; extra == 'gradio'
Requires-Dist: gradio-log; extra == 'gradio'
Requires-Dist: gradio[oauth]==5.15.0; extra == 'gradio'
